arxiv_latex_cleaner/__init__.py
arxiv_latex_cleaner/__main__.py
arxiv_latex_cleaner/_version.py
arxiv_latex_cleaner/arxiv_latex_cleaner.py
arxiv_latex_cleaner-1.0.8.dist-info/LICENSE
arxiv_latex_cleaner-1.0.8.dist-info/METADATA
arxiv_latex_cleaner-1.0.8.dist-info/WHEEL
arxiv_latex_cleaner-1.0.8.dist-info/entry_points.txt
arxiv_latex_cleaner-1.0.8.dist-info/top_level.txt
arxiv_latex_cleaner-1.0.8.dist-info/RECORD
