Metadata-Version: 2.1
Name: arxiv_latex_cleaner
Version: 1.0.8
Summary: Cleans the LaTeX code of your paper to submit to arXiv.
Home-page: https://github.com/google-research/arxiv-latex-cleaner
Author: Google Research Authors
Author-email: jponttuset@gmail.com
License: Apache License, Version 2.0
Classifier: License :: OSI Approved :: Apache Software License
Classifier: Intended Audience :: Science/Research
Requires-Python: >=3
License-File: LICENSE
Requires-Dist: absl-py >=0.12
Requires-Dist: pillow
Requires-Dist: pyyaml
Requires-Dist: regex
